main.py
cmmt-0.1.0.dist-info/licenses/LICENSE
cmmt-0.1.0.dist-info/METADATA
cmmt-0.1.0.dist-info/WHEEL
cmmt-0.1.0.dist-info/entry_points.txt
cmmt-0.1.0.dist-info/top_level.txt
cmmt-0.1.0.dist-info/RECORD
