Metadata-Version: 2.4
Name: cmmt
Version: 0.1.0
Summary: AI-powered commit messages and branch naming.
Requires-Python: >=3.13
License-File: LICENSE
Requires-Dist: openai>=2.14.0
Requires-Dist: tiktoken>=0.5.0
Requires-Dist: PyYAML>=6.0
Requires-Dist: httpx[socks]>=0.28.1
Dynamic: license-file
